morebs2/__init__.py
morebs2/aprng_gauge.py
morebs2/ball_clump_data_generator.py
morebs2/ball_clump_data_generator_test.py
morebs2/ball_comp.py
morebs2/ball_comp_components.py
morebs2/ball_comp_test_cases.py
morebs2/ball_operator.py
morebs2/ball_operator_navigation_test.py
morebs2/ball_operator_split_test.py
morebs2/ball_operator_test_cases.py
morebs2/ball_volume_estimators.py
morebs2/chained_poly_interpolation.py
morebs2/deline.py
morebs2/deline_helpers.py
morebs2/deline_mc.py
morebs2/distributions.py
morebs2/fit_2n2.py
morebs2/g2tdecomp.py
morebs2/globalls.py
morebs2/graph_basics.py
morebs2/hop_pattern.py
morebs2/line.py
morebs2/matrix_methods.py
morebs2/measures.py
morebs2/message_streamer.py
morebs2/modular_labeller.py
morebs2/numerical_extras.py
morebs2/numerical_generator.py
morebs2/numerical_space_data_generator.py
morebs2/onedimprt_classifier.py
morebs2/point_sorter.py
morebs2/point_weight_function.py
morebs2/poly_factor.py
morebs2/poly_interpolation.py
morebs2/poly_struct.py
morebs2/random_generators.py
morebs2/relevance_functions.py
morebs2/relevance_functions_extended.py
morebs2/rssi.py
morebs2/rssi_components.py
morebs2/search_space_iterator.py
morebs2/seq_repr.py
morebs2/set_merger.py
morebs2/travel_data.py
morebs2/variance_works.py
morebs2/violation_handler.py
morebs2/tests/__init__.py
morebs2/tests/aprng_gauge_test.py
morebs2/tests/ball_comp_components_test.py
morebs2/tests/ball_comp_components_test_cases.py
morebs2/tests/ball_comp_test.py
morebs2/tests/chained_poly_interpolation_test.py
morebs2/tests/deline_test.py
morebs2/tests/fit_2n2_test.py
morebs2/tests/g2tdecomp_test.py
morebs2/tests/graph_basics_test.py
morebs2/tests/graph_basics_test_cases.py
morebs2/tests/hop_pattern_test.py
morebs2/tests/matrix_methods__bounds__test.py
morebs2/tests/message_streamer_test.py
morebs2/tests/numerical_generator_test.py
morebs2/tests/numerical_space_data_generator_test.py
morebs2/tests/onedimprt_classifier_test.py
morebs2/tests/point_sorter_test.py
morebs2-0.1.50.dist-info/licenses/LICENSE
morebs2-0.1.50.dist-info/METADATA
morebs2-0.1.50.dist-info/WHEEL
morebs2-0.1.50.dist-info/top_level.txt
morebs2-0.1.50.dist-info/RECORD
